Metadata-Version: 2.1
Name: matrixorbital-vfd
Version: 0.1.1
Summary: I2C display driver for Matrix Orbital VFDs
Home-page: https://github.com/derekn/matrixorbital-vfd
Author: Derek Nicol
Author-email: derekn85@gmail.com
License: MIT
Keywords: matrix orbital vfd vacuum fluorescent display i2c smbus
Platform: UNKNOWN
Classifier: Development Status :: 4 - Beta
Classifier: Intended Audience :: Developers
Classifier: License :: OSI Approved :: MIT License
Classifier: Programming Language :: Python :: 3
Classifier: Programming Language :: Python :: 3.4
Classifier: Programming Language :: Python :: 3.5
Classifier: Programming Language :: Python :: 3.6
Classifier: Programming Language :: Python :: 3.7
Classifier: Programming Language :: Python :: 3.8
Classifier: Programming Language :: Python :: 3.9
Classifier: Topic :: Software Development :: Libraries
Classifier: Topic :: System :: Hardware
Classifier: Topic :: Utilities
Requires-Python: >=3.4.0
License-File: LICENSE
